{
    "version": "3.4.5",
    "release_date": "2026-05-02",
    "file_url": "https://github.com/codegatr/wisecp-codega-theme/archive/refs/heads/main.zip",
    "details_url": "https://github.com/codegatr/wisecp-codega-theme/releases/tag/v3.4.5-codega",
    "tag": "v3.4.5-codega",
    "changelog": [
        "v3.4.5 - KRITIK: Musteri paneli tarama + 4 buyuk duzeltme",
        "FIX: ac-product-domain.php DNS gorunmuyordu",
        "  $options['nameservers']/['ns'] yerine $options['ns1'..'ns4'] kullaniliyor",
        "  Form name=ns1,ns2 yerine name=dns[] dizi formati (Classic uyumlu)",
        "  Geri uyumluluk: nameservers/ns array'leri de denenir",
        "  ARTIK musteri DNS degisikligini gorur ve kaydedebilir",
        "REWRITE: ac-info.php (168 -> 527 satir) - Hesap bilgileri sayfasi",
        "  Eski: operation=update_settings (yanlis), name+surname (yanlis)",
        "  Yeni: operation=ModifyAccountInfo (Classic ile uyumlu)",
        "  3 tab: Profil / Sifre Degistir / Guvenlik Sorusu",
        "  Bireysel/Kurumsal toggle (kind: individual/corporate)",
        "  Eklenen alanlar: full_name, gsm, landline_phone, birthday, identity (TC),",
        "    company_name/tax_office/tax_number, country_id, counti (ilce),",
        "    cfields[] (ozel alanlar), security_question/answer",
        "  E-posta ve GSM dogrulama rozet gosterimi",
        "  Editable kontrolu (her alan icin disabled durumu)",
        "  Sifre formu ayri operation=ModifyPassword (sifre gucu meter)",
        "  Guvenlik sorusu icin ayri tab",
        "ENH: inc/ac-product-detail-template.php (hosting/server paket detaylari)",
        "  Yeni 'Paket Kotalari' karti: disk, bandwidth, email, database, ftp,",
        "    subdomain, addon, park, cpu, ram, max_email_per_hour limitleri",
        "  Renkli grid layout (8+ kota - icon+renk kombinasyonu)",
        "  'Sinirsiz' tespiti ve gosterim",
        "  'Sunucu DNS Bilgileri' karti ($options['dns'] array'inden)",
        "  'Teknik Bilgiler' karti: panel_type, FTP host/port/username,",
        "    creation_info[date]",
        "ENH: inc/ac-software-extras.php Lisans Bilgileri karti",
        "  Yeni: lisans kodu (kopyala butonu), lisans IP, ozel parametreler",
        "  $options['code'], $options['ip'], $license_parameters okunmaya basladi",
        "  WiseCP runtime: $options['code'], $options['ip'], $license_parameters",
        "Tum operation key'leri Classic ile uyumlu hale getirildi"
    ]
}
